[
    {
        "name" : "ルナ",
        "breed" : "スコティッシュフォールド",
        "gender" : "メス"
    },
    {
        "name" : "ソラ",
        "breed" : "マンチカン",
        "gender" : "オス"
    },
    {
        "name" : "モカ",
        "breed" : "ラグドール",
        "gender" : "メス"
    },
    {
        "name" : "ベル",
        "breed" : "ノルウェージャンフォレストキャット",
        "gender" : "メス"
    },
    {
        "name" : "リン",
        "breed" : "ブリティッシュショートヘア",
        "gender" : "メス"
    },
    {
        "name" : "ノア",
        "breed" : "メインクーン",
        "gender" : "オス"
    }
]